baka_model/__init__.py
baka_model/service.py
baka_model/model/__init__.py
baka_model/model/helper.py
baka_model/model/pubid.py
baka_model/model/meta/__init__.py
baka_model/model/meta/base.py
baka_model/model/meta/orm.py
baka_model/model/meta/schema.py
baka_model/model/meta/type.py
baka_model-0.18.7.dist-info/DESCRIPTION.rst
baka_model-0.18.7.dist-info/METADATA
baka_model-0.18.7.dist-info/RECORD
baka_model-0.18.7.dist-info/WHEEL
baka_model-0.18.7.dist-info/metadata.json
baka_model-0.18.7.dist-info/top_level.txt
