Metadata-Version: 2.0
Name: baka-model
Version: 0.18.7
Summary: Baka: Skeleton framework built top of pyramid, baka_model for sqlalchemy
Home-page: https://github.com/suryakencana/baka_model
Author: Nanang Suryadi
Author-email: nanang.jobs@gmail.com
License: MIT
Download-URL: https://github.com/suryakencana/baka_model/archive/0.17.1.tar.gz
Keywords: model,sqlalchemy,framework
Platform: UNKNOWN
Classifier: Development Status :: 3 - Alpha
Classifier: Environment :: Web Environment
Classifier: Framework :: Pyramid
Classifier: Intended Audience :: Developers
Classifier: Topic :: Software Development :: Libraries
Classifier: License :: OSI Approved :: MIT License
Classifier: Programming Language :: Python :: 2
Classifier: Programming Language :: Python :: 2.6
Classifier: Programming Language :: Python :: 2.7
Classifier: Programming Language :: Python :: 3
Classifier: Programming Language :: Python :: 3.2
Classifier: Programming Language :: Python :: 3.3
Classifier: Programming Language :: Python :: 3.4
Classifier: Operating System :: OS Independent
Requires-Dist: awesome-slugify
Requires-Dist: bcrypt
Requires-Dist: pyramid
Requires-Dist: pyramid-retry
Requires-Dist: pyramid-tm
Requires-Dist: python-dateutil
Requires-Dist: python-dateutil
Requires-Dist: setuptools
Requires-Dist: sqlalchemy
Requires-Dist: sqlalchemy-utils
Requires-Dist: transaction
Requires-Dist: zope.sqlalchemy
